infino_sdk/__init__.py
infino_sdk/lib.py
infino_sdk-0.4.1.dist-info/licenses/LICENSE
infino_sdk-0.4.1.dist-info/METADATA
infino_sdk-0.4.1.dist-info/WHEEL
infino_sdk-0.4.1.dist-info/top_level.txt
infino_sdk-0.4.1.dist-info/RECORD
